{
  "Unit Tests": {
    "coverage": {
      "/Users/mikeheft/turing/mod1/projects/complete_me/lib/node.rb": [
        1,
        1,
        null,
        1,
        11,
        11,
        null,
        null,
        1,
        5,
        null,
        null
      ],
      "/Users/mikeheft/turing/mod1/projects/complete_me/lib/trie.rb": [
        1,
        null,
        1,
        1,
        null,
        1,
        4,
        4,
        null,
        null,
        1,
        1,
        1,
        5,
        1,
        null,
        4,
        null,
        null,
        1,
        1,
        null,
        null,
        null
      ]
    },
    "timestamp": 1499545153
  }
}
